relquant/__init__.py
relquant/measures.py
relquant-0.0.1.dist-info/LICENSE
relquant-0.0.1.dist-info/METADATA
relquant-0.0.1.dist-info/WHEEL
relquant-0.0.1.dist-info/top_level.txt
relquant-0.0.1.dist-info/RECORD
