Metadata-Version: 2.1
Name: relquant
Version: 0.0.1
Summary: A package for quantifying relation properties.
Author-email: Galen Seilis <galen.seilis@seilis.ca>
Project-URL: Homepage, https://github.com/galenseilis/relquant
Project-URL: Bug Tracker, https://github.com/galenseilis/relquant/issues
Classifier: Programming Language :: Python :: 3
Classifier: License :: OSI Approved :: MIT License
Classifier: Operating System :: OS Independent
Requires-Python: >=3.7
License-File: LICENSE
